Metadata-Version: 1.1
Name: django-promo
Version: 1.2.0a3
Summary: A reuseable Django application for coupon gereration and handling.
Home-page: https://github.com/ashwineaso/django-promo
Author: ashwineaso
Author-email: root@ashwineaso.com
License: The MIT License (MIT)
